TittaLSLPy_v1.cpython-38-x86_64-linux-gnu.so
TittaLSLPy_v2.cpython-38-x86_64-linux-gnu.so
tittalslpy.libs/libavahi-client-373b7738.so.3.2.9
tittalslpy.libs/libavahi-common-91518825.so.3.5.4
tittalslpy.libs/libcap-6500f43e.so.2.48
tittalslpy.libs/libdbus-1-43555f95.so.3.19.13
tittalslpy.libs/libgcrypt-3098dcde.so.20.4.0
tittalslpy.libs/libgpg-error-df6ee685.so.0.32.0
tittalslpy.libs/liblsl-61715b03.so
tittalslpy.libs/liblz4-9ba322f5.so.1.9.3
tittalslpy.libs/liblzma-270e41f3.so.5.2.5
tittalslpy.libs/libsystemd-c5cae820.so.0.35.0
tittalslpy.libs/libtobii_research-37413a8c.so.2
tittalslpy.libs/libtobii_research-a85796b1.so.1
tittalslpy.libs/libzstd-82d8f7e0.so.1.5.5
tittalslpy-2.0.0.dist-info/METADATA
tittalslpy-2.0.0.dist-info/WHEEL
tittalslpy-2.0.0.dist-info/top_level.txt
tittalslpy-2.0.0.dist-info/RECORD
