Metadata-Version: 2.4
Name: TittaLSLPy
Version: 2.0.0
Summary: Interface for streaming and receiving Tobii eye tracker data using Lab Streaming Layer
Home-page: https://github.com/dcnieho/Titta
Author: Diederick C. Niehorster
Author-email: diederick_c.niehorster@humlab.lu.se
Keywords: Tobii PsychoPy Eye-tracking streaming remote LSL
Classifier: Development Status :: 5 - Production/Stable
Classifier: Intended Audience :: Science/Research
Classifier: Topic :: Scientific/Engineering
Classifier: Topic :: Software Development :: Libraries
Classifier: Environment :: MacOS X
Classifier: Environment :: Win32 (MS Windows)
Classifier: Environment :: X11 Applications
Classifier: Operating System :: Microsoft :: Windows
Classifier: Operating System :: MacOS :: MacOS X
Classifier: Operating System :: POSIX :: Linux
Classifier: Programming Language :: Python :: 3
Classifier: Programming Language :: C++
Requires-Python: >=3.8
Requires-Dist: numpy
Requires-Dist: TittaPy==2.0.0
Dynamic: author
Dynamic: author-email
Dynamic: classifier
Dynamic: description
Dynamic: description-content-type
Dynamic: home-page
Dynamic: keywords
Dynamic: requires-dist
Dynamic: requires-python
Dynamic: summary
